LICENSE.txt
MANIFEST.in
README.rst
Tool.py
setup.py
prtestlib.egg-info/PKG-INFO
prtestlib.egg-info/SOURCES.txt
prtestlib.egg-info/dependency_links.txt
prtestlib.egg-info/top_level.txt
sztestlib/__init__.py
sztestlib/szlibone.py