Metadata-Version: 1.0
Name: prtestlib
Version: 1.0.1
Summary: This is a excellent lib
Home-page: https://caiseyingzi.com
Author: Sz
Author-email: caiseyingzi@gmail.com
License: MIT
Platform: UNKNOWN
